<parties last_id="0">
  <partie id="0">
    <titre>Saign&#233;e M&#233;diterran&#233;enne</titre>
    <capacite>6</capacite>
    <minimum>1</minimum>
    <inscrits>6</inscrits>
    <date>2021-07-25</date>
    <heure>21h00</heure>
    <duree>3h30</duree>
    <type>Campagne</type>
    <mj>Syn#3950</mj>
    <systeme>Vampire</systeme>
    <pjMineur>Non</pjMineur>
    <plateformes>Discord</plateformes>
    <details>Saison 3 - Chapitre 1 : Nouvelle donne.

5 ans se sont écoulées, Nice est envahie par la Seconde Inquisition en raison des actions de Vivaldo. La présence importante de chasseurs de vampires a obligée les semblables à se terrer et chercher de nouvelles sources de financement. La plupart se sont tournés vers le crime organisé, créant ainsi des tensions entre les clans. Aujourd'hui, la cité est sur le point d'imploser et la découverte d'un cadavre calciné risque de la diviser complètement...</details>
    <lien>https://discord.com/channels/298887769793757184/410049488816701450/864963544004821022</lien>
  </partie>
</parties>